{"/":{"style.231d9.css":{"type":"style","weight":1},"bundle.08b3a.js":{"type":"script","weight":1},"route-home.chunk.bdd2c.js":{"type":"script","weight":0.9}},"/profile":{"style.231d9.css":{"type":"style","weight":1},"bundle.08b3a.js":{"type":"script","weight":1},"route-profile.chunk.8f36b.js":{"type":"script","weight":0.9}},"/management":{"style.231d9.css":{"type":"style","weight":1},"bundle.08b3a.js":{"type":"script","weight":1},"route-management.chunk.a70bc.js":{"type":"script","weight":0.9}},"/ip":{"style.231d9.css":{"type":"style","weight":1},"bundle.08b3a.js":{"type":"script","weight":1},"route-ip.chunk.9a9f7.js":{"type":"script","weight":0.9}}}